nclpy/__init__.py
nclpy/basemaps.py
nclpy/common.py
nclpy/generate_points.py
nclpy/nclpy.py
nclpy/toolbar.py
nclpy/utils.py
nclpy-0.0.11.dist-info/LICENSE
nclpy-0.0.11.dist-info/METADATA
nclpy-0.0.11.dist-info/WHEEL
nclpy-0.0.11.dist-info/dependency_links.txt
nclpy-0.0.11.dist-info/top_level.txt
nclpy-0.0.11.dist-info/RECORD
