Metadata-Version: 2.1
Name: nclpy
Version: 0.0.11
Summary: A Python package for working with NCL
Home-page: https://github.com/HJRubin/nclpy
Author: Hannah Rubin
Author-email: hannahrubin100@gmail.com
License: MIT license
Keywords: nclpy
Platform: UNKNOWN
Classifier: Development Status :: 2 - Pre-Alpha
Classifier: Intended Audience :: Developers
Classifier: License :: OSI Approved :: MIT License
Classifier: Natural Language :: English
Classifier: Programming Language :: Python :: 3
Classifier: Programming Language :: Python :: 3.5
Classifier: Programming Language :: Python :: 3.6
Classifier: Programming Language :: Python :: 3.7
Classifier: Programming Language :: Python :: 3.8
Requires-Python: >=3.5
Requires-Dist: earthengine-api
Requires-Dist: folium
Requires-Dist: ipyfilechooser
Requires-Dist: python-box
Requires-Dist: ipyleaflet
Requires-Dist: pyshp
